{"_values": ["Creator     : groff version 1.22.4", "CreationDate: Tue Feb  1 14:18:38 2022", "html PUBLIC \"-//W3C//DTD HTML 4.01 Transitional//EN\"\n\"http://www.w3.org/TR/html4/loose.dtd\""], "html": [{"head": [{"meta": [{"_attributes": {"name": "generator", "content": "groff -Thtml, see www.gnu.org"}}, {"_attributes": {"http-equiv": "Content-Type", "content": "text/html; charset=US-ASCII"}}, {"_attributes": {"name": "Content-Style", "content": "text/css"}}], "style": [{"_attributes": {"type": "text/css"}, "_value": "p       { margin-top: 0; margin-bottom: 0; vertical-align: top }\n       pre     { margin-top: 0; margin-bottom: 0; vertical-align: top }\n       table   { margin-top: 0; margin-bottom: 0; vertical-align: top }\n       h1      { text-align: center }"}], "title": [{"_value": "PASSWD"}]}], "body": [{"h1": [{"_attributes": {"align": "center"}, "_value": "PASSWD"}], "a": [{"_attributes": {"href": "#NAME"}, "_value": "NAME"}, {"_attributes": {"href": "#SYNOPSIS"}, "_value": "SYNOPSIS"}, {"_attributes": {"href": "#DESCRIPTION"}, "_value": "DESCRIPTION"}, {"_attributes": {"href": "#OPTIONS"}, "_value": "OPTIONS"}, {"_attributes": {"href": "#EXAMPLES"}, "_value": "EXAMPLES"}], "br": [{}, {}, {}, {}, {}], "hr": [{}, {}], "h2": [{"_value": "NAME", "a": [{"_attributes": {"name": "NAME"}}]}, {"_value": "SYNOPSIS", "a": [{"_attributes": {"name": "SYNOPSIS"}}]}, {"_value": "DESCRIPTION", "a": [{"_attributes": {"name": "DESCRIPTION"}}]}, {"_value": "OPTIONS", "a": [{"_attributes": {"name": "OPTIONS"}}]}, {"_value": "EXAMPLES", "a": [{"_attributes": {"name": "EXAMPLES"}}]}], "p": [{"_attributes": {"style": "margin-left:11%; margin-top: 1em"}, "_value": "passwd -\ncompute password hashes"}, {"_attributes": {"style": "margin-left:11%; margin-top: 1em"}, "b": [{"_value": "openssl\npasswd"}, {"_value": "-crypt"}, {"_value": "-1"}, {"_value": "-apr1"}, {"_value": "-salt"}, {"_value": "-in"}, {"_value": "-stdin"}, {"_value": "-noverify"}, {"_value": "-quiet"}, {"_value": "-table"}], "_values": ["[", "] [", "] [", "]\n[", "] [", "]\n[", "] [", "] [", "]\n[", "] {", "}"], "i": [{"_value": "string"}, {"_value": "file"}, {"_value": "password"}]}, {"_attributes": {"style": "margin-left:11%; margin-top: 1em"}, "b": [{"_value": "passwd"}, {"_value": "-in\nfile"}, {"_value": "-stdin"}, {"_value": "crypt"}, {"_value": "1"}, {"_value": "apr1"}], "_values": ["The", "command computes the hash of a password typed\nat run-time or the hash of each password in a list. The\npassword list is taken from the named file for option", ", from stdin for option", ", or from the\ncommand line, or from the terminal otherwise. The Unix\nstandard algorithm", "and the MD5-based", "password algorithm", "and its\nApache variant", "are available."], "small": [{"_value": "BSD"}]}, {"_attributes": {"style": "margin-left:11%; margin-top: 1em"}, "b": [{"_value": "-crypt"}]}, {"_attributes": {"style": "margin-left:17%;"}, "b": [{"_value": "crypt"}], "_values": ["Use the", "algorithm\n(default)."]}, {"_attributes": {"style": "margin-left:11%;"}, "b": [{"_value": "-apr1"}]}, {"_attributes": {"style": "margin-left:17%;"}, "b": [{"_value": "apr1"}], "_values": ["Use the", "algorithm\n(Apache variant of the", "algorithm)."], "small": [{"_value": "BSD"}]}, {"_attributes": {"style": "margin-left:11%;"}, "b": [{"_value": "-salt"}], "i": [{"_value": "string"}]}, {"_attributes": {"style": "margin-left:17%;"}, "b": [{"_value": "-noverify"}], "_values": ["Use the specified salt. When\nreading a password from the terminal, this implies", "."]}, {"_attributes": {"style": "margin-left:11%;"}, "b": [{"_value": "-in"}], "i": [{"_value": "file"}]}, {"_attributes": {"style": "margin-left:17%;"}, "i": [{"_value": "file"}], "_values": ["Read passwords from", "."]}, {"_attributes": {"style": "margin-left:11%;"}, "b": [{"_value": "-stdin"}]}, {"_attributes": {"style": "margin-left:17%;"}, "b": [{"_value": "stdin"}], "_values": ["Read passwords from", "."]}, {"_attributes": {"style": "margin-left:11%;"}, "b": [{"_value": "-noverify"}]}, {"_attributes": {"style": "margin-left:17%;"}, "_value": "Don\u2019t verify when reading\na password from the terminal."}, {"_attributes": {"style": "margin-left:11%;"}, "b": [{"_value": "-quiet"}]}, {"_attributes": {"style": "margin-left:17%;"}, "_value": "Don\u2019t output warnings\nwhen passwords given at the command line are truncated."}, {"_attributes": {"style": "margin-left:11%;"}, "b": [{"_value": "-table"}]}, {"_attributes": {"style": "margin-left:17%;"}, "small": [{"_value": "TAB"}], "_values": ["In the output list, prepend the\ncleartext password and a", "character to\neach password hash."]}, {"_attributes": {"style": "margin-left:11%; margin-top: 1em"}, "b": [{"_value": "openssl\npasswd -crypt -salt xx password"}, {"_value": "xxj31ZMTZzkVA"}], "_values": ["prints", "."]}, {"_attributes": {"style": "margin-left:11%; margin-top: 1em"}, "b": [{"_value": "openssl\npasswd -1 -salt xxxxxxxx password"}, {"_value": "$1$xxxxxxxx$UYCIxa628.9qXjpQCjM4a."}], "_values": ["prints", "."]}, {"_attributes": {"style": "margin-left:11%; margin-top: 1em"}, "b": [{"_value": "openssl\npasswd -apr1 -salt xxxxxxxx password"}, {"_value": "$apr1$xxxxxxxx$dxHfLAsjHkDRmG83UXe8K0"}], "_values": ["prints", "."]}], "table": [{"_attributes": {"width": "100%", "border": "0", "rules": "none", "frame": "void", "cellspacing": "0", "cellpadding": "0"}, "tr": [{"_attributes": {"valign": "top", "align": "left"}, "td": [{"_attributes": {"width": "11%"}}, {"_attributes": {"width": "3%"}, "p": [{"b": [{"_value": "-1"}]}]}, {"_attributes": {"width": "3%"}}, {"_attributes": {"width": "66%"}, "p": [{"small": [{"_value": "MD5"}, {"_value": "BSD"}], "_values": ["Use the", "based", "password algorithm", "."], "b": [{"_value": "1"}]}]}, {"_attributes": {"width": "17%"}}]}]}]}]}]}