{"_values": ["Creator     : groff version 1.22.4", "CreationDate: Tue Feb  1 14:18:45 2022", "html PUBLIC \"-//W3C//DTD HTML 4.01 Transitional//EN\"\n\"http://www.w3.org/TR/html4/loose.dtd\""], "html": [{"head": [{"meta": [{"_attributes": {"name": "generator", "content": "groff -Thtml, see www.gnu.org"}}, {"_attributes": {"http-equiv": "Content-Type", "content": "text/html; charset=US-ASCII"}}, {"_attributes": {"name": "Content-Style", "content": "text/css"}}], "style": [{"_attributes": {"type": "text/css"}, "_value": "p       { margin-top: 0; margin-bottom: 0; vertical-align: top }\n       pre     { margin-top: 0; margin-bottom: 0; vertical-align: top }\n       table   { margin-top: 0; margin-bottom: 0; vertical-align: top }\n       h1      { text-align: center }"}], "title": [{"_value": "VERIFY"}]}], "body": [{"h1": [{"_attributes": {"align": "center"}, "_value": "VERIFY"}], "a": [{"_attributes": {"href": "#NAME"}, "_value": "NAME"}, {"_attributes": {"href": "#SYNOPSIS"}, "_value": "SYNOPSIS"}, {"_attributes": {"href": "#DESCRIPTION"}, "_value": "DESCRIPTION"}, {"_attributes": {"href": "#COMMAND OPTIONS"}, "_value": "COMMAND OPTIONS"}, {"_attributes": {"href": "#VERIFY OPERATION"}, "_value": "VERIFY OPERATION"}, {"_attributes": {"href": "#DIAGNOSTICS"}, "_value": "DIAGNOSTICS"}, {"_attributes": {"href": "#BUGS"}, "_value": "BUGS"}, {"_attributes": {"href": "#SEE ALSO"}, "_value": "SEE ALSO"}, {"_attributes": {"href": "#HISTORY"}, "_value": "HISTORY"}], "br": [{}, {}, {}, {}, {}, {}, {}, {}, {}], "hr": [{}, {}], "h2": [{"_value": "NAME", "a": [{"_attributes": {"name": "NAME"}}]}, {"_value": "SYNOPSIS", "a": [{"_attributes": {"name": "SYNOPSIS"}}]}, {"_value": "DESCRIPTION", "a": [{"_attributes": {"name": "DESCRIPTION"}}]}, {"_value": "COMMAND OPTIONS", "a": [{"_attributes": {"name": "COMMAND OPTIONS"}}]}, {"_value": "VERIFY OPERATION", "a": [{"_attributes": {"name": "VERIFY OPERATION"}}]}, {"_value": "DIAGNOSTICS", "a": [{"_attributes": {"name": "DIAGNOSTICS"}}]}, {"_value": "BUGS", "a": [{"_attributes": {"name": "BUGS"}}]}, {"_value": "SEE ALSO", "a": [{"_attributes": {"name": "SEE ALSO"}}]}, {"_value": "HISTORY", "a": [{"_attributes": {"name": "HISTORY"}}]}], "p": [{"_attributes": {"style": "margin-left:11%; margin-top: 1em"}, "_value": "verify -\nUtility to verify certificates."}, {"_attributes": {"style": "margin-left:11%; margin-top: 1em"}, "b": [{"_value": "openssl\nverify"}, {"_value": "-CApath directory"}, {"_value": "-CAfile file"}, {"_value": "-purpose purpose"}, {"_value": "-policy arg"}, {"_value": "-ignore_critical"}, {"_value": "-crl_check"}, {"_value": "-crl_check_all"}, {"_value": "-policy_check"}, {"_value": "-explicit_policy"}, {"_value": "-inhibit_any"}, {"_value": "-inhibit_map"}, {"_value": "-x509_strict"}, {"_value": "-extended_crl"}, {"_value": "-use_deltas"}, {"_value": "-policy_print"}, {"_value": "-no_alt_chains"}, {"_value": "-allow_proxy_certs"}, {"_value": "-untrusted file"}, {"_value": "-help"}, {"_value": "-issuer_checks"}, {"_value": "-attime\ntimestamp"}, {"_value": "-verbose"}, {"_value": "-"}], "_values": ["[", "] [", "]\n[", "] [", "]\n[", "] [", "]\n[", "] [", "]\n[", "] [", "]\n[", "] [", "]\n[", "] [", "]\n[", "] [", "]\n[", "] [", "]\n[", "] [", "] [", "] [", "] [", "]\n[certificates]"]}, {"_attributes": {"style": "margin-left:11%; margin-top: 1em"}, "b": [{"_value": "verify"}], "_values": ["The", "command verifies certificate chains."]}, {"_attributes": {"style": "margin-left:11%; margin-top: 1em"}, "b": [{"_value": "-CApath\ndirectory"}]}, {"_attributes": {"style": "margin-left:17%;"}, "b": [{"_value": "-hash"}, {"_value": "x509"}, {"_value": "c_rehash"}], "_values": ["A directory of trusted\ncertificates. The certificates should have names of the\nform: hash.0 or have symbolic links to them of this form\n(\"hash\" is the hashed certificate subject name:\nsee the", "option of the", "utility).\nUnder Unix the", "script will automatically\ncreate symbolic links to a directory of certificates."]}, {"_attributes": {"style": "margin-left:11%;"}, "b": [{"_value": "-CAfile file"}, {"br": [{}], "_value": "-untrusted file"}], "br": [{}], "_values": ["A file of\ntrusted certificates. The file should contain", "multiple certificates in", "format\nconcatenated together."], "small": [{"_value": "PEM"}]}, {"_attributes": {"style": "margin-left:17%;"}, "small": [{"_value": "PEM"}], "_values": ["A file of untrusted\ncertificates. The file should contain multiple certificates\nin", "format concatenated together."]}, {"_attributes": {"style": "margin-left:11%;"}, "b": [{"_value": "-purpose purpose"}]}, {"_attributes": {"style": "margin-left:17%;"}, "b": [{"_value": "verify"}, {"_value": "sslclient"}, {"_value": "sslserver"}, {"_value": "nssslserver"}, {"_value": "smimesign"}, {"_value": "smimeencrypt"}, {"small": [{"_value": "VERIFY\nOPERATION"}]}], "_values": ["The intended use for the\ncertificate. If this option is not specified,", "will not consider certificate purpose during chain\nverification. Currently accepted uses are", ",", ",", ",", ",", ". See the", "section for more information."]}, {"_attributes": {"style": "margin-left:11%;"}, "b": [{"_value": "-help"}]}, {"_attributes": {"style": "margin-left:17%;"}, "_value": "Print out a usage message."}, {"_attributes": {"style": "margin-left:11%;"}, "b": [{"_value": "-verbose"}]}, {"_attributes": {"style": "margin-left:17%;"}, "_value": "Print extra information about\nthe operations being performed."}, {"_attributes": {"style": "margin-left:11%;"}, "b": [{"_value": "-issuer_checks"}]}, {"_attributes": {"style": "margin-left:17%;"}, "_value": "Print out diagnostics relating\nto searches for the issuer certificate of the current\ncertificate. This shows why each candidate issuer\ncertificate was rejected. The presence of rejection messages\ndoes not itself imply that anything is wrong; during the\nnormal verification process, several rejections may take\nplace."}, {"_attributes": {"style": "margin-left:11%;"}, "b": [{"_value": "-attime timestamp"}]}, {"_attributes": {"style": "margin-left:17%;"}, "b": [{"_value": "timestamp"}, {"_value": "timestamp"}], "_values": ["Perform validation checks using\ntime specified by", "and not current system\ntime.", "is the number of seconds since\n01.01.1970 (", "time)."], "small": [{"_value": "UNIX"}]}, {"_attributes": {"style": "margin-left:11%;"}, "b": [{"_value": "-policy arg"}]}, {"_attributes": {"style": "margin-left:17%;"}, "b": [{"_value": "arg"}, {"_value": "arg"}], "_values": ["Enable policy processing and\nadd", "to the user-initial-policy-set (see", "). The policy", "can be an\nobject name an", "in numeric form. This\nargument can appear more than once."], "small": [{"_value": "RFC5280"}, {"_value": "OID"}]}, {"_attributes": {"style": "margin-left:11%;"}, "b": [{"_value": "-policy_check"}]}, {"_attributes": {"style": "margin-left:17%;"}, "_value": "Enables certificate policy\nprocessing."}, {"_attributes": {"style": "margin-left:11%;"}, "b": [{"_value": "-explicit_policy"}]}, {"_attributes": {"style": "margin-left:17%;"}, "small": [{"_value": "RFC5280"}], "_values": ["Set policy variable\nrequire-explicit-policy (see", ")."]}, {"_attributes": {"style": "margin-left:11%;"}, "b": [{"_value": "-inhibit_any"}]}, {"_attributes": {"style": "margin-left:17%;"}, "small": [{"_value": "RFC5280"}], "_values": ["Set policy variable\ninhibit-any-policy (see", ")."]}, {"_attributes": {"style": "margin-left:11%;"}, "b": [{"_value": "-inhibit_map"}]}, {"_attributes": {"style": "margin-left:17%;"}, "small": [{"_value": "RFC5280"}], "_values": ["Set policy variable\ninhibit-policy-mapping (see", ")."]}, {"_attributes": {"style": "margin-left:11%;"}, "b": [{"_value": "-no_alt_chains"}]}, {"_attributes": {"style": "margin-left:17%;"}, "_value": "When building a certificate\nchain, if the first certificate chain found is not trusted,\nthen OpenSSL will continue to check to see if an alternative\nchain can be found that is trusted. With this option that\nbehaviour is suppressed so that only the first chain found\nis ever used. Using this option will force the behaviour to\nmatch that of previous OpenSSL versions."}, {"_attributes": {"style": "margin-left:11%;"}, "b": [{"_value": "-allow_proxy_certs"}]}, {"_attributes": {"style": "margin-left:17%;"}, "_value": "Allow the verification of proxy\ncertificates."}, {"_attributes": {"style": "margin-left:11%;"}, "b": [{"_value": "-policy_print"}]}, {"_attributes": {"style": "margin-left:17%;"}, "_value": "Print out diagnostics related\nto policy processing."}, {"_attributes": {"style": "margin-left:11%;"}, "b": [{"_value": "-crl_check"}]}, {"_attributes": {"style": "margin-left:17%;"}, "small": [{"_value": "CRL."}, {"_value": "CRL"}], "_values": ["Checks end entity certificate\nvalidity by attempting to look up a valid", "If a valid", "cannot be\nfound an error occurs."]}, {"_attributes": {"style": "margin-left:11%;"}, "b": [{"_value": "-crl_check_all"}]}, {"_attributes": {"style": "margin-left:17%;"}, "b": [{"_value": "all"}], "_values": ["Checks the validity of", "certificates in the chain by attempting to look\nup valid CRLs."]}, {"_attributes": {"style": "margin-left:11%;"}, "b": [{"_value": "-ignore_critical"}]}, {"_attributes": {"style": "margin-left:17%;"}, "small": [{"_value": "RFC5280"}], "_values": ["Normally if an unhandled\ncritical extension is present which is not supported by\nOpenSSL the certificate is rejected (as required by", "). If this option is set critical\nextensions are ignored."]}, {"_attributes": {"style": "margin-left:11%;"}, "b": [{"_value": "-x509_strict"}]}, {"_attributes": {"style": "margin-left:17%;"}, "_value": "For strict X.509 compliance,\ndisable non-compliant workarounds for broken\ncertificates."}, {"_attributes": {"style": "margin-left:11%;"}, "b": [{"_value": "-extended_crl"}]}, {"_attributes": {"style": "margin-left:17%;"}, "small": [{"_value": "CRL"}, {"_value": "CRL"}], "_values": ["Enable extended", "features such as indirect CRLs and\nalternate", "signing keys."]}, {"_attributes": {"style": "margin-left:11%;"}, "b": [{"_value": "-use_deltas"}]}, {"_attributes": {"style": "margin-left:17%;"}, "_value": "Enable support for delta\nCRLs."}, {"_attributes": {"style": "margin-left:11%;"}, "b": [{"_value": "-check_ss_sig"}]}, {"_attributes": {"style": "margin-left:17%;"}, "small": [{"_value": "CA."}], "_values": ["Verify the signature on the\nself-signed root", "This is disabled by\ndefault because it doesn\u2019t add any security."]}, {"_attributes": {"style": "margin-left:11%;"}, "b": [{"_value": "certificates"}]}, {"_attributes": {"style": "margin-left:17%;"}, "b": [{"_value": "verify"}], "_values": ["One or more certificates to\nverify. If no certificates are given,", "will\nattempt to read a certificate from standard input.\nCertificates must be in", "format."], "small": [{"_value": "PEM"}]}, {"_attributes": {"style": "margin-left:11%; margin-top: 1em"}, "b": [{"_value": "verify"}], "_values": ["The", "program uses the same functions as the\ninternal", "and S/MIME verification,\ntherefore this description applies to these verify\noperations too."], "small": [{"_value": "SSL"}]}, {"_attributes": {"style": "margin-left:11%; margin-top: 1em"}, "b": [{"_value": "verify"}], "_values": ["There is one\ncrucial difference between the verify operations performed\nby the", "program: wherever possible an attempt\nis made to continue after an error whereas normally the\nverify operation would halt on the first error. This allows\nall the problems with a certificate chain to be\ndetermined."]}, {"_attributes": {"style": "margin-left:11%; margin-top: 1em"}, "_value": "The verify\noperation consists of a number of separate steps."}, {"_attributes": {"style": "margin-left:11%; margin-top: 1em"}, "small": [{"_value": "CA."}, {"_value": "CA."}], "_values": ["Firstly a\ncertificate chain is built up starting from the supplied\ncertificate and ending in the root", "It is\nan error if the whole chain cannot be built up. The chain is\nbuilt up by looking up the issuers certificate of the\ncurrent certificate. If a certificate is found which is its\nown issuer it is assumed to be the root"]}, {"_attributes": {"style": "margin-left:11%; margin-top: 1em"}, "_value": "The process of\n\u2019looking up the issuers certificate\u2019 itself\ninvolves a number of steps. In versions of OpenSSL before\n0.9.5a the first certificate whose subject name matched the\nissuer of the current certificate was assumed to be the\nissuers certificate. In OpenSSL 0.9.6 and later all\ncertificates whose subject name matches the issuer name of\nthe current certificate are subject to further tests. The\nrelevant authority key identifier components of the current\ncertificate (if present) must match the subject key\nidentifier (if present) and issuer and serial number of the\ncandidate issuer, in addition the keyUsage extension of the\ncandidate issuer (if present) must permit certificate\nsigning."}, {"_attributes": {"style": "margin-left:11%; margin-top: 1em"}, "small": [{"_value": "CA"}], "_values": ["The lookup\nfirst looks in the list of untrusted certificates and if no\nmatch is found the remaining lookups are from the trusted\ncertificates. The root", "is always looked up\nin the trusted certificate list: if the certificate to\nverify is a root certificate then an exact match must be\nfound in the trusted list."]}, {"_attributes": {"style": "margin-left:11%; margin-top: 1em"}, "b": [{"_value": "-purpose"}, {"small": [{"_value": "CERTIFICATE\nEXTENSIONS"}]}, {"_value": "x509"}], "_values": ["The second\noperation is to check every untrusted certificate\u2019s\nextensions for consistency with the supplied purpose. If the", "option is not included then no checks are\ndone. The supplied or \"leaf\" certificate must have\nextensions compatible with the supplied purpose and all\nother certificates must also be valid", "certificates. The precise extensions required are described\nin more detail in the", "section of the", "utility."], "small": [{"_value": "CA"}]}, {"_attributes": {"style": "margin-left:11%; margin-top: 1em"}, "small": [{"_value": "CA."}, {"_value": "CA"}], "_values": ["The third\noperation is to check the trust settings on the root", "The root", "should be\ntrusted for the supplied purpose. For compatibility with\nprevious versions of SSLeay and OpenSSL a certificate with\nno trust settings is considered to be valid for all\npurposes."]}, {"_attributes": {"style": "margin-left:11%; margin-top: 1em"}, "_value": "The final\noperation is to check the validity of the certificate chain.\nThe validity period is checked against the current system\ntime and the notBefore and notAfter dates in the\ncertificate. The certificate signatures are also checked at\nthis point."}, {"_attributes": {"style": "margin-left:11%; margin-top: 1em"}, "_value": "If all\noperations complete successfully then certificate is\nconsidered valid. If any operation fails then the\ncertificate is not valid."}, {"_attributes": {"style": "margin-left:11%; margin-top: 1em"}, "_value": "When a verify\noperation fails the output messages can be somewhat cryptic.\nThe general form of the error message is:"}, {"_attributes": {"style": "margin-left:11%; margin-top: 1em"}, "br": [{}], "_values": ["server.pem:\n/C=AU/ST=Queensland/O=CryptSoft Pty Ltd/CN=Test CA (1024\nbit)", "error 24 at 1 depth lookup:invalid CA certificate"]}, {"_attributes": {"style": "margin-left:11%; margin-top: 1em"}, "small": [{"_value": "CA"}], "_values": ["The first line\ncontains the name of the certificate being verified followed\nby the subject name of the certificate. The second line\ncontains the error number and the depth. The depth is number\nof the certificate being verified when a problem was\ndetected starting with zero for the certificate being\nverified itself then 1 for the", "that signed\nthe certificate and so on. Finally a text version of the\nerror number is presented."]}, {"_attributes": {"style": "margin-left:11%; margin-top: 1em"}, "_value": "An exhaustive\nlist of the error codes and messages is shown below, this\nalso includes the name of the error code as defined in the\nheader file x509_vfy.h Some of the error codes are defined\nbut never returned: these are described as\n\"unused\".", "b": [{"br": [{}], "_value": "0 X509_V_OK: ok"}]}, {"_attributes": {"style": "margin-left:17%;"}, "_value": "the operation was\nsuccessful."}, {"_attributes": {"style": "margin-left:11%;"}, "b": [{"br": [{}], "_values": ["2\nX509_V_ERR_UNABLE_TO_GET_ISSUER_CERT: unable to get issuer", "certificate"]}]}, {"_attributes": {"style": "margin-left:17%;"}, "_value": "the issuer certificate of a\nlooked up certificate could not be found. This normally\nmeans the list of trusted certificates is not complete."}, {"_attributes": {"style": "margin-left:11%;"}, "b": [{"_value": "3\nX509_V_ERR_UNABLE_TO_GET_CRL: unable to get certificate", "small": [{"_value": "CRL"}]}]}, {"_attributes": {"style": "margin-left:17%;"}, "small": [{"_value": "CRL"}], "_values": ["the", "of a\ncertificate could not be found."]}, {"_attributes": {"style": "margin-left:11%;"}, "b": [{"br": [{}], "_values": ["4\nX509_V_ERR_UNABLE_TO_DECRYPT_CERT_SIGNATURE: unable to\ndecrypt", "certificate\u2019s signature"]}]}, {"_attributes": {"style": "margin-left:17%;"}, "small": [{"_value": "RSA"}], "_values": ["the certificate signature could\nnot be decrypted. This means that the actual signature value\ncould not be determined rather than it not matching the\nexpected value, this is only meaningful for", "keys."]}, {"_attributes": {"style": "margin-left:11%;"}, "b": [{"small": [{"_value": "CRL"}], "_values": ["5\nX509_V_ERR_UNABLE_TO_DECRYPT_CRL_SIGNATURE: unable to\ndecrypt", "\u2019s", "signature"], "br": [{}]}]}, {"_attributes": {"style": "margin-left:17%;"}, "small": [{"_value": "CRL"}], "_values": ["the", "signature could not be decrypted: this means that the actual\nsignature value could not be determined rather than it not\nmatching the expected value. Unused."]}, {"_attributes": {"style": "margin-left:11%;"}, "b": [{"br": [{}], "_values": ["6\nX509_V_ERR_UNABLE_TO_DECODE_ISSUER_PUBLIC_KEY: unable to\ndecode", "issuer public key"]}]}, {"_attributes": {"style": "margin-left:17%;"}, "_value": "the public key in the\ncertificate SubjectPublicKeyInfo could not be read."}, {"_attributes": {"style": "margin-left:11%;"}, "b": [{"_value": "7\nX509_V_ERR_CERT_SIGNATURE_FAILURE: certificate signature\nfailure"}]}, {"_attributes": {"style": "margin-left:17%;"}, "_value": "the signature of the\ncertificate is invalid."}, {"_attributes": {"style": "margin-left:11%;"}, "b": [{"small": [{"_value": "CRL"}], "_values": ["8\nX509_V_ERR_CRL_SIGNATURE_FAILURE:", "signature failure"]}]}, {"_attributes": {"style": "margin-left:17%;"}, "_value": "the signature of the\ncertificate is invalid."}, {"_attributes": {"style": "margin-left:11%;"}, "b": [{"_value": "9\nX509_V_ERR_CERT_NOT_YET_VALID: certificate is not yet\nvalid"}]}, {"_attributes": {"style": "margin-left:17%;"}, "_value": "the certificate is not yet\nvalid: the notBefore date is after the current time."}, {"_attributes": {"style": "margin-left:11%;"}, "b": [{"_value": "10\nX509_V_ERR_CERT_HAS_EXPIRED: certificate has expired"}]}, {"_attributes": {"style": "margin-left:17%;"}, "_value": "the certificate has expired:\nthat is the notAfter date is before the current time."}, {"_attributes": {"style": "margin-left:11%;"}, "b": [{"small": [{"_value": "CRL"}], "_values": ["11\nX509_V_ERR_CRL_NOT_YET_VALID:", "is not yet\nvalid"]}]}, {"_attributes": {"style": "margin-left:17%;"}, "small": [{"_value": "CRL"}], "_values": ["the", "is not\nyet valid."]}, {"_attributes": {"style": "margin-left:11%;"}, "b": [{"small": [{"_value": "CRL"}], "_values": ["12\nX509_V_ERR_CRL_HAS_EXPIRED:", "has\nexpired"]}]}, {"_attributes": {"style": "margin-left:17%;"}, "small": [{"_value": "CRL"}], "_values": ["the", "has\nexpired."]}, {"_attributes": {"style": "margin-left:11%;"}, "b": [{"br": [{}], "_values": ["13\nX509_V_ERR_ERROR_IN_CERT_NOT_BEFORE_FIELD: format error in", "certificate\u2019s notBefore field"]}]}, {"_attributes": {"style": "margin-left:17%;"}, "_value": "the certificate notBefore field\ncontains an invalid time."}, {"_attributes": {"style": "margin-left:11%;"}, "b": [{"br": [{}], "_values": ["14\nX509_V_ERR_ERROR_IN_CERT_NOT_AFTER_FIELD: format error in", "certificate\u2019s notAfter field"]}]}, {"_attributes": {"style": "margin-left:17%;"}, "_value": "the certificate notAfter field\ncontains an invalid time."}, {"_attributes": {"style": "margin-left:11%;"}, "b": [{"small": [{"_value": "CRL"}], "_values": ["15\nX509_V_ERR_ERROR_IN_CRL_LAST_UPDATE_FIELD: format error in", "\u2019s", "lastUpdate field"], "br": [{}]}]}, {"_attributes": {"style": "margin-left:17%;"}, "small": [{"_value": "CRL"}], "_values": ["the", "lastUpdate field contains an invalid time."]}, {"_attributes": {"style": "margin-left:11%;"}, "b": [{"small": [{"_value": "CRL"}], "_values": ["16\nX509_V_ERR_ERROR_IN_CRL_NEXT_UPDATE_FIELD: format error in", "\u2019s", "nextUpdate field"], "br": [{}]}]}, {"_attributes": {"style": "margin-left:17%;"}, "small": [{"_value": "CRL"}], "_values": ["the", "nextUpdate field contains an invalid time."]}, {"_attributes": {"style": "margin-left:11%;"}, "b": [{"_value": "17 X509_V_ERR_OUT_OF_MEM:\nout of memory"}]}, {"_attributes": {"style": "margin-left:17%;"}, "_value": "an error occurred trying to\nallocate memory. This should never happen."}, {"_attributes": {"style": "margin-left:11%;"}, "b": [{"_value": "18\nX509_V_ERR_DEPTH_ZERO_SELF_SIGNED_CERT: self signed\ncertificate"}]}, {"_attributes": {"style": "margin-left:17%;"}, "_value": "the passed certificate is self\nsigned and the same certificate cannot be found in the list\nof trusted certificates."}, {"_attributes": {"style": "margin-left:11%;"}, "b": [{"br": [{}], "_values": ["19\nX509_V_ERR_SELF_SIGNED_CERT_IN_CHAIN: self signed\ncertificate in", "certificate chain"]}]}, {"_attributes": {"style": "margin-left:17%;"}, "_value": "the certificate chain could be\nbuilt up using the untrusted certificates but the root could\nnot be found locally."}, {"_attributes": {"style": "margin-left:11%;"}, "b": [{"br": [{}], "_values": ["20\nX509_V_ERR_UNABLE_TO_GET_ISSUER_CERT_LOCALLY: unable to get\nlocal", "issuer certificate"]}]}, {"_attributes": {"style": "margin-left:17%;"}, "_value": "the issuer certificate could\nnot be found: this occurs if the issuer certificate of an\nuntrusted certificate cannot be found."}, {"_attributes": {"style": "margin-left:11%;"}, "b": [{"br": [{}], "_values": ["21\nX509_V_ERR_UNABLE_TO_VERIFY_LEAF_SIGNATURE: unable to verify\nthe", "first certificate"]}]}, {"_attributes": {"style": "margin-left:17%;"}, "_value": "no signatures could be verified\nbecause the chain contains only one certificate and it is\nnot self signed."}, {"_attributes": {"style": "margin-left:11%;"}, "b": [{"_value": "22\nX509_V_ERR_CERT_CHAIN_TOO_LONG: certificate chain too\nlong"}]}, {"_attributes": {"style": "margin-left:17%;"}, "_value": "the certificate chain length is\ngreater than the supplied maximum depth. Unused."}, {"_attributes": {"style": "margin-left:11%;"}, "b": [{"_value": "23 X509_V_ERR_CERT_REVOKED:\ncertificate revoked"}]}, {"_attributes": {"style": "margin-left:17%;"}, "_value": "the certificate has been\nrevoked."}, {"_attributes": {"style": "margin-left:11%;"}, "b": [{"small": [{"_value": "CA"}], "_values": ["24 X509_V_ERR_INVALID_CA:\ninvalid", "certificate"]}]}, {"_attributes": {"style": "margin-left:17%;"}, "small": [{"_value": "CA"}, {"_value": "CA"}], "_values": ["a", "certificate\nis invalid. Either it is not a", "or its\nextensions are not consistent with the supplied purpose."]}, {"_attributes": {"style": "margin-left:11%;"}, "b": [{"_value": "25\nX509_V_ERR_PATH_LENGTH_EXCEEDED: path length constraint\nexceeded"}]}, {"_attributes": {"style": "margin-left:17%;"}, "_value": "the basicConstraints pathlength\nparameter has been exceeded."}, {"_attributes": {"style": "margin-left:11%;"}, "b": [{"_value": "26\nX509_V_ERR_INVALID_PURPOSE: unsupported certificate\npurpose"}]}, {"_attributes": {"style": "margin-left:17%;"}, "_value": "the supplied certificate cannot\nbe used for the specified purpose."}, {"_attributes": {"style": "margin-left:11%;"}, "b": [{"_value": "27\nX509_V_ERR_CERT_UNTRUSTED: certificate not trusted"}]}, {"_attributes": {"style": "margin-left:17%;"}, "small": [{"_value": "CA"}], "_values": ["the root", "is\nnot marked as trusted for the specified purpose."]}, {"_attributes": {"style": "margin-left:11%;"}, "b": [{"_value": "28 X509_V_ERR_CERT_REJECTED:\ncertificate rejected"}]}, {"_attributes": {"style": "margin-left:17%;"}, "small": [{"_value": "CA"}], "_values": ["the root", "is\nmarked to reject the specified purpose."]}, {"_attributes": {"style": "margin-left:11%;"}, "b": [{"_value": "29\nX509_V_ERR_SUBJECT_ISSUER_MISMATCH: subject issuer\nmismatch"}]}, {"_attributes": {"style": "margin-left:17%;"}, "b": [{"_value": "-issuer_checks"}], "_values": ["the current candidate issuer\ncertificate was rejected because its subject name did not\nmatch the issuer name of the current certificate. Only\ndisplayed when the", "option is set."]}, {"_attributes": {"style": "margin-left:11%;"}, "b": [{"br": [{}], "_values": ["30\nX509_V_ERR_AKID_SKID_MISMATCH: authority and subject key\nidentifier", "mismatch"]}]}, {"_attributes": {"style": "margin-left:17%;"}, "b": [{"_value": "-issuer_checks"}], "_values": ["the current candidate issuer\ncertificate was rejected because its subject key identifier\nwas present and did not match the authority key identifier\ncurrent certificate. Only displayed when the", "option is set."]}, {"_attributes": {"style": "margin-left:11%;"}, "b": [{"br": [{}], "_values": ["31\nX509_V_ERR_AKID_ISSUER_SERIAL_MISMATCH: authority and issuer\nserial", "number mismatch"]}]}, {"_attributes": {"style": "margin-left:17%;"}, "b": [{"_value": "-issuer_checks"}], "_values": ["the current candidate issuer\ncertificate was rejected because its issuer name and serial\nnumber was present and did not match the authority key\nidentifier of the current certificate. Only displayed when\nthe", "option is set."]}, {"_attributes": {"style": "margin-left:11%;"}, "b": [{"br": [{}], "_values": ["32\nX509_V_ERR_KEYUSAGE_NO_CERTSIGN:key usage does not include", "certificate signing"]}]}, {"_attributes": {"style": "margin-left:17%;"}, "_value": "the current candidate issuer\ncertificate was rejected because its keyUsage extension does\nnot permit certificate signing."}, {"_attributes": {"style": "margin-left:11%;"}, "b": [{"br": [{}], "_values": ["50\nX509_V_ERR_APPLICATION_VERIFICATION: application\nverification", "failure"]}]}, {"_attributes": {"style": "margin-left:17%;"}, "_value": "an application specific error.\nUnused."}, {"_attributes": {"style": "margin-left:11%; margin-top: 1em"}, "small": [{"_value": "API."}], "_values": ["Although the\nissuer checks are a considerable improvement over the old\ntechnique they still suffer from limitations in the\nunderlying X509_LOOKUP", "One consequence\nof this is that trusted certificates with matching subject\nname must either appear in a file (as specified by the", "option) or a directory (as specified by", ". If they occur in both then only the\ncertificates in the file will be recognised."], "b": [{"_value": "-CAfile"}, {"_value": "-CApath"}]}, {"_attributes": {"style": "margin-left:11%; margin-top: 1em"}, "_value": "Previous\nversions of OpenSSL assume certificates with matching\nsubject name are identical and mishandled them."}, {"_attributes": {"style": "margin-left:11%; margin-top: 1em"}, "b": [{"_value": "X509_V_ERR_UNABLE_TO_GET_ISSUER_CERT"}, {"_value": "20\nX509_V_ERR_UNABLE_TO_GET_ISSUER_CERT_LOCALLY"}], "_values": ["Previous\nversions of this documentation swapped the meaning of the", "and", "error\ncodes."]}, {"_attributes": {"style": "margin-left:11%; margin-top: 1em"}, "b": [{"_value": "x509"}], "_value": "(1)"}, {"_attributes": {"style": "margin-left:11%; margin-top: 1em"}, "_value": "The\n-no_alt_chains options was first added to OpenSSL 1.0.1n and\n1.0.2b."}], "table": [{"_attributes": {"width": "100%", "border": "0", "rules": "none", "frame": "void", "cellspacing": "0", "cellpadding": "0"}, "tr": [{"_attributes": {"valign": "top", "align": "left"}, "td": [{"_attributes": {"width": "11%"}}, {"_attributes": {"width": "1%"}, "p": [{"b": [{"_value": "-"}]}]}, {"_attributes": {"width": "5%"}}, {"_attributes": {"width": "83%"}, "p": [{"b": [{"_value": "-"}], "_values": ["Indicates the last option. All arguments following this\nare assumed to be certificate files. This is useful if the\nfirst certificate filename begins with a", "."]}]}]}]}]}]}]}